[
  {
    "id": "110292",
    "gen": "female",
    "rel": "Muslim",
    "eng": "Jinani",
    "FLeng": "J",
    "tel": "జనని",
    "FLtel": "జ"
  },
  {
    "id": "110293",
    "gen": "female",
    "rel": "Hindu",
    "eng": "Jinarshee",
    "FLeng": "J",
    "tel": "జినార్షీ",
    "FLtel": "జ"
  },
  {
    "id": "110294",
    "gen": "female",
    "rel": "Hindu",
    "eng": "Jincy",
    "FLeng": "J",
    "tel": "జిన్సీ",
    "FLtel": "జ"
  },
  {
    "id": "110295",
    "gen": "female",
    "rel": "Hindu",
    "eng": "Jindal",
    "FLeng": "J",
    "tel": "జిందాల్",
    "FLtel": "జ"
  },
  {
    "id": "110296",
    "gen": "female",
    "rel": "Christian",
    "eng": "Jindoiska",
    "FLeng": "J",
    "tel": "జిందుఇస్క",
    "FLtel": "జ"
  },
  {
    "id": "110297",
    "gen": "female",
    "rel": "Christian",
    "eng": "Jinelle",
    "FLeng": "J",
    "tel": "జినెళ్ళే",
    "FLtel": "జ"
  },
  {
    "id": "110298",
    "gen": "female",
    "rel": "Christian",
    "eng": "Jinger",
    "FLeng": "J",
    "tel": "జింజర్",
    "FLtel": "జ"
  },
  {
    "id": "110299",
    "gen": "female",
    "rel": "Hindu",
    "eng": "Jini",
    "FLeng": "J",
    "tel": "జిని",
    "FLtel": "జ"
  },
  {
    "id": "110300",
    "gen": "female",
    "rel": "Christian",
    "eng": "Jinia",
    "FLeng": "J",
    "tel": "జిని",
    "FLtel": "జ"
  },
  {
    "id": "110301",
    "gen": "female",
    "rel": "Hindu",
    "eng": "Jinisha",
    "FLeng": "J",
    "tel": "జినీషా",
    "FLtel": "జ"
  },
  {
    "id": "110302",
    "gen": "female",
    "rel": "Hindu",
    "eng": "Jinita",
    "FLeng": "J",
    "tel": "జోనిటా",
    "FLtel": "జ"
  },
  {
    "id": "110303",
    "gen": "female",
    "rel": "Christian",
    "eng": "Jiniya",
    "FLeng": "J",
    "tel": "జోనియా",
    "FLtel": "జ"
  },
  {
    "id": "110304",
    "gen": "female",
    "rel": "Hindu",
    "eng": "Jinkal",
    "FLeng": "J",
    "tel": "జింకల",
    "FLtel": "జ"
  },
  {
    "id": "110305",
    "gen": "female",
    "rel": "Hindu",
    "eng": "Jinnat",
    "FLeng": "J",
    "tel": "జన్నత్",
    "FLtel": "జ"
  },
  {
    "id": "110306",
    "gen": "female",
    "rel": "Christian",
    "eng": "Jinni",
    "FLeng": "J",
    "tel": "జిన్ని",
    "FLtel": "జ"
  },
  {
    "id": "110307",
    "gen": "female",
    "rel": "Christian",
    "eng": "Jinny",
    "FLeng": "J",
    "tel": "జన్నీ",
    "FLtel": "జ"
  },
  {
    "id": "110308",
    "gen": "female",
    "rel": "Hindu",
    "eng": "Jinsha",
    "FLeng": "J",
    "tel": "జింశ",
    "FLtel": "జ"
  },
  {
    "id": "110309",
    "gen": "female",
    "rel": "Christian",
    "eng": "Jinx",
    "FLeng": "J",
    "tel": "జింక్",
    "FLtel": "జ"
  },
  {
    "id": "110310",
    "gen": "female",
    "rel": "Christian",
    "eng": "Jioina",
    "FLeng": "J",
    "tel": "జివోయిన",
    "FLtel": "జ"
  },
  {
    "id": "110311",
    "gen": "female",
    "rel": "Christian",
    "eng": "Jioni",
    "FLeng": "J",
    "tel": "జీవుని",
    "FLtel": "జ"
  },
  {
    "id": "110312",
    "gen": "female",
    "rel": "Christian",
    "eng": "Jionni",
    "FLeng": "J",
    "tel": "జీవుణ్ణి",
    "FLtel": "జ"
  },
  {
    "id": "110313",
    "gen": "female",
    "rel": "Christian",
    "eng": "Jira",
    "FLeng": "J",
    "tel": "జీరా",
    "FLtel": "జ"
  },
  {
    "id": "110314",
    "gen": "female",
    "rel": "Christian",
    "eng": "Jiraiya",
    "FLeng": "J",
    "tel": "జిరియా",
    "FLtel": "జ"
  },
  {
    "id": "110315",
    "gen": "female",
    "rel": "Christian",
    "eng": "jirina",
    "FLeng": "j",
    "tel": "జరీనా",
    "FLtel": "జ"
  },
  {
    "id": "110316",
    "gen": "female",
    "rel": "Christian",
    "eng": "Jiselle",
    "FLeng": "J",
    "tel": "జోసెల్లె",
    "FLtel": "జ"
  },
  {
    "id": "110317",
    "gen": "female",
    "rel": "Hindu",
    "eng": "Jisha",
    "FLeng": "J",
    "tel": "జైషే",
    "FLtel": "జ"
  },
  {
    "id": "110318",
    "gen": "female",
    "rel": "Hindu",
    "eng": "Jishitha",
    "FLeng": "J",
    "tel": "జోషిత",
    "FLtel": "జ"
  },
  {
    "id": "110319",
    "gen": "female",
    "rel": "Hindu",
    "eng": "Jishmol",
    "FLeng": "J",
    "tel": "జిష్మోల్",
    "FLtel": "జ"
  },
  {
    "id": "110320",
    "gen": "female",
    "rel": "Hindu",
    "eng": "Jishwikha",
    "FLeng": "J",
    "tel": "జిశ్విక",
    "FLtel": "జ"
  },
  {
    "id": "110321",
    "gen": "female",
    "rel": "Christian",
    "eng": "Jisinia",
    "FLeng": "J",
    "tel": "జోషిని",
    "FLtel": "జ"
  },
  {
    "id": "110322",
    "gen": "female",
    "rel": "Hindu",
    "eng": "Jissy",
    "FLeng": "J",
    "tel": "జిసిసి",
    "FLtel": "జ"
  },
  {
    "id": "110323",
    "gen": "female",
    "rel": "Hindu",
    "eng": "jitha",
    "FLeng": "j",
    "tel": "జిత",
    "FLtel": "జ"
  },
  {
    "id": "110324",
    "gen": "female",
    "rel": "Hindu",
    "eng": "Jithi",
    "FLeng": "J",
    "tel": "జోతి",
    "FLtel": "జ"
  },
  {
    "id": "110325",
    "gen": "female",
    "rel": "Hindu",
    "eng": "Jithisha",
    "FLeng": "J",
    "tel": "జోతిష",
    "FLtel": "జ"
  },
  {
    "id": "110326",
    "gen": "female",
    "rel": "Hindu",
    "eng": "Jithya",
    "FLeng": "J",
    "tel": "జిత్య",
    "FLtel": "జ"
  },
  {
    "id": "110327",
    "gen": "female",
    "rel": "Hindu",
    "eng": "Jiti",
    "FLeng": "J",
    "tel": "జిటి",
    "FLtel": "జ"
  },
  {
    "id": "110328",
    "gen": "female",
    "rel": "Christian",
    "eng": "Jitka",
    "FLeng": "J",
    "tel": "జట్కా",
    "FLtel": "జ"
  },
  {
    "id": "110329",
    "gen": "female",
    "rel": "Christian",
    "eng": "jitka",
    "FLeng": "j",
    "tel": "జట్కా",
    "FLtel": "జ"
  },
  {
    "id": "110330",
    "gen": "female",
    "rel": "Hindu",
    "eng": "Jitya",
    "FLeng": "J",
    "tel": "జిత్య",
    "FLtel": "జ"
  },
  {
    "id": "110331",
    "gen": "female",
    "rel": "Hindu",
    "eng": "Jiu",
    "FLeng": "J",
    "tel": "జిఉ",
    "FLtel": "జ"
  },
  {
    "id": "110332",
    "gen": "female",
    "rel": "Christian",
    "eng": "Jivanta",
    "FLeng": "J",
    "tel": "జీవంత",
    "FLtel": "జ"
  },
  {
    "id": "110333",
    "gen": "female",
    "rel": "Hindu",
    "eng": "jivanta",
    "FLeng": "j",
    "tel": "జీవంత",
    "FLtel": "జ"
  },
  {
    "id": "110334",
    "gen": "female",
    "rel": "Hindu",
    "eng": "Jivanthika",
    "FLeng": "J",
    "tel": "జీవంతిక",
    "FLtel": "జ"
  },
  {
    "id": "110335",
    "gen": "female",
    "rel": "Hindu",
    "eng": "Jivantika",
    "FLeng": "J",
    "tel": "జీవంతిక",
    "FLtel": "జ"
  },
  {
    "id": "110336",
    "gen": "female",
    "rel": "Christian",
    "eng": "Jivatha",
    "FLeng": "J",
    "tel": "జీవత",
    "FLtel": "జ"
  },
  {
    "id": "110337",
    "gen": "female",
    "rel": "Hindu",
    "eng": "Jivati",
    "FLeng": "J",
    "tel": "జీవతి",
    "FLtel": "జ"
  },
  {
    "id": "110338",
    "gen": "female",
    "rel": "Hindu",
    "eng": "Jiveeka",
    "FLeng": "J",
    "tel": "జీవీకే",
    "FLtel": "జ"
  },
  {
    "id": "110339",
    "gen": "female",
    "rel": "Hindu",
    "eng": "Jivi",
    "FLeng": "J",
    "tel": "జివి",
    "FLtel": "జ"
  },
  {
    "id": "110340",
    "gen": "female",
    "rel": "Hindu",
    "eng": "Jivika",
    "FLeng": "J",
    "tel": "జీవిక",
    "FLtel": "జ"
  },
  {
    "id": "110341",
    "gen": "female",
    "rel": "Hindu",
    "eng": "Jivinta",
    "FLeng": "J",
    "tel": "జీవింతా",
    "FLtel": "జ"
  },
  {
    "id": "110342",
    "gen": "female",
    "rel": "Hindu",
    "eng": "Jivita",
    "FLeng": "J",
    "tel": "జీవిత",
    "FLtel": "జ"
  },
  {
    "id": "110343",
    "gen": "female",
    "rel": "Christian",
    "eng": "Jiwal",
    "FLeng": "J",
    "tel": "జివాల్",
    "FLtel": "జ"
  },
  {
    "id": "110344",
    "gen": "female",
    "rel": "Hindu",
    "eng": "Jiya",
    "FLeng": "J",
    "tel": "జియా",
    "FLtel": "జ"
  },
  {
    "id": "110345",
    "gen": "female",
    "rel": "Christian",
    "eng": "Jiya ram",
    "FLeng": "J",
    "tel": "జియా రామ్",
    "FLtel": "జ"
  },
  {
    "id": "110346",
    "gen": "female",
    "rel": "Hindu",
    "eng": "Jiya Ushas",
    "FLeng": "J",
    "tel": "జియా ఉషస్",
    "FLtel": "జ"
  },
  {
    "id": "110347",
    "gen": "female",
    "rel": "Hindu",
    "eng": "Jiyana",
    "FLeng": "J",
    "tel": "జియానా",
    "FLtel": "జ"
  },
  {
    "id": "110348",
    "gen": "female",
    "rel": "Hindu",
    "eng": "Jiyanshi",
    "FLeng": "J",
    "tel": "జియాంశ",
    "FLtel": "జ"
  },
  {
    "id": "110349",
    "gen": "female",
    "rel": "Christian",
    "eng": "Jiyaram",
    "FLeng": "J",
    "tel": "జయరాం",
    "FLtel": "జ"
  },
  {
    "id": "110350",
    "gen": "female",
    "rel": "Christian",
    "eng": "Jnateya",
    "FLeng": "J",
    "tel": "జ్ఞాతీయ",
    "FLtel": "జ"
  },
  {
    "id": "110351",
    "gen": "female",
    "rel": "Christian",
    "eng": "Jo",
    "FLeng": "J",
    "tel": "జో",
    "FLtel": "జ"
  },
  {
    "id": "110352",
    "gen": "female",
    "rel": "Christian",
    "eng": "Joaida",
    "FLeng": "J",
    "tel": "జోయిదా",
    "FLtel": "జ"
  },
  {
    "id": "110353",
    "gen": "female",
    "rel": "Christian",
    "eng": "Joan",
    "FLeng": "J",
    "tel": "జోన్",
    "FLtel": "జ"
  },
  {
    "id": "110354",
    "gen": "female",
    "rel": "Christian",
    "eng": "Joana",
    "FLeng": "J",
    "tel": "జొన్నా",
    "FLtel": "జ"
  },
  {
    "id": "110355",
    "gen": "female",
    "rel": "Sikh",
    "eng": "Joane",
    "FLeng": "J",
    "tel": "జోనే",
    "FLtel": "జ"
  },
  {
    "id": "110356",
    "gen": "female",
    "rel": "Christian",
    "eng": "Joanelle",
    "FLeng": "J",
    "tel": "జోనేల్లె",
    "FLtel": "జ"
  },
  {
    "id": "110357",
    "gen": "female",
    "rel": "Christian",
    "eng": "Joanie",
    "FLeng": "J",
    "tel": "జోఅనియే",
    "FLtel": "జ"
  },
  {
    "id": "110358",
    "gen": "female",
    "rel": "Christian",
    "eng": "joanie",
    "FLeng": "j",
    "tel": "జోఅనియే",
    "FLtel": "జ"
  },
  {
    "id": "110359",
    "gen": "female",
    "rel": "Christian",
    "eng": "Joaninha",
    "FLeng": "J",
    "tel": "జోయాణింహ",
    "FLtel": "జ"
  },
  {
    "id": "110360",
    "gen": "female",
    "rel": "Christian",
    "eng": "Joanka",
    "FLeng": "J",
    "tel": "జొఅంక",
    "FLtel": "జ"
  },
  {
    "id": "110361",
    "gen": "female",
    "rel": "Christian",
    "eng": "Joann",
    "FLeng": "J",
    "tel": "జోన్",
    "FLtel": "జ"
  },
  {
    "id": "110362",
    "gen": "female",
    "rel": "Christian",
    "eng": "joann",
    "FLeng": "j",
    "tel": "జోన్",
    "FLtel": "జ"
  },
  {
    "id": "110363",
    "gen": "female",
    "rel": "others",
    "eng": "Joanna",
    "FLeng": "J",
    "tel": "జోన్నీ",
    "FLtel": "జ"
  },
  {
    "id": "110364",
    "gen": "female",
    "rel": "Christian",
    "eng": "Joanne",
    "FLeng": "J",
    "tel": "జోయాన్నే",
    "FLtel": "జ"
  },
  {
    "id": "110365",
    "gen": "female",
    "rel": "Christian",
    "eng": "Joannee",
    "FLeng": "J",
    "tel": "జోయాన్నీ",
    "FLtel": "జ"
  },
  {
    "id": "110366",
    "gen": "female",
    "rel": "Christian",
    "eng": "Joannie",
    "FLeng": "J",
    "tel": "జోఅన్నిఏ",
    "FLtel": "జ"
  },
  {
    "id": "110367",
    "gen": "female",
    "rel": "Christian",
    "eng": "Joarder",
    "FLeng": "J",
    "tel": "జోయార్డర్",
    "FLtel": "జ"
  },
  {
    "id": "110368",
    "gen": "female",
    "rel": "Christian",
    "eng": "joasia",
    "FLeng": "j",
    "tel": "జోయాసియా",
    "FLtel": "జ"
  },
  {
    "id": "110369",
    "gen": "female",
    "rel": "Christian",
    "eng": "jobeth",
    "FLeng": "j",
    "tel": "జోబెత్",
    "FLtel": "జ"
  },
  {
    "id": "110370",
    "gen": "female",
    "rel": "Christian",
    "eng": "Jobina",
    "FLeng": "J",
    "tel": "జోబీనా",
    "FLtel": "జ"
  },
  {
    "id": "110371",
    "gen": "female",
    "rel": "others",
    "eng": "Jocasta",
    "FLeng": "J",
    "tel": "జోకేస్తా",
    "FLtel": "జ"
  },
  {
    "id": "110372",
    "gen": "female",
    "rel": "Christian",
    "eng": "Jocatta",
    "FLeng": "J",
    "tel": "జాకెట్ట",
    "FLtel": "జ"
  },
  {
    "id": "110373",
    "gen": "female",
    "rel": "Christian",
    "eng": "Jocea",
    "FLeng": "J",
    "tel": "జొసీ",
    "FLtel": "జ"
  },
  {
    "id": "110374",
    "gen": "female",
    "rel": "Christian",
    "eng": "Joceleyn",
    "FLeng": "J",
    "tel": "జోసెలెవైన్",
    "FLtel": "జ"
  },
  {
    "id": "110375",
    "gen": "female",
    "rel": "Christian",
    "eng": "Jocelin",
    "FLeng": "J",
    "tel": "జోసెలిన్",
    "FLtel": "జ"
  },
  {
    "id": "110376",
    "gen": "female",
    "rel": "Christian",
    "eng": "Joceline",
    "FLeng": "J",
    "tel": "జోసెలిన్",
    "FLtel": "జ"
  },
  {
    "id": "110377",
    "gen": "female",
    "rel": "Christian",
    "eng": "Jocellyn",
    "FLeng": "J",
    "tel": "జోసెలీన్",
    "FLtel": "జ"
  },
  {
    "id": "110378",
    "gen": "female",
    "rel": "Christian",
    "eng": "Jocelyn",
    "FLeng": "J",
    "tel": "జోసెలైన్",
    "FLtel": "జ"
  },
  {
    "id": "110379",
    "gen": "female",
    "rel": "Christian",
    "eng": "Jocelyne",
    "FLeng": "J",
    "tel": "జోసెలైన్",
    "FLtel": "జ"
  },
  {
    "id": "110380",
    "gen": "female",
    "rel": "Christian",
    "eng": "Jocelynn",
    "FLeng": "J",
    "tel": "జోసెలైన్",
    "FLtel": "జ"
  },
  {
    "id": "110381",
    "gen": "female",
    "rel": "Christian",
    "eng": "jocelynn",
    "FLeng": "j",
    "tel": "జోసెలైన్",
    "FLtel": "జ"
  },
  {
    "id": "110382",
    "gen": "female",
    "rel": "Christian",
    "eng": "Jochebed",
    "FLeng": "J",
    "tel": "జొచేబెడ్",
    "FLtel": "జ"
  }
]