[
  {
    "id": "139148",
    "gen": "female",
    "rel": "Christian",
    "eng": "Brianna",
    "FLeng": "B",
    "tel": "బ్రియన్న",
    "FLtel": "బ"
  },
  {
    "id": "139149",
    "gen": "female",
    "rel": "Christian",
    "eng": "Briannah",
    "FLeng": "B",
    "tel": "బ్రిఅన్నహ్",
    "FLtel": "బ"
  },
  {
    "id": "139150",
    "gen": "female",
    "rel": "Christian",
    "eng": "Brianne",
    "FLeng": "B",
    "tel": "బ్రియాన్నే",
    "FLtel": "బ"
  },
  {
    "id": "139151",
    "gen": "female",
    "rel": "Christian",
    "eng": "Briannika",
    "FLeng": "B",
    "tel": "బ్రిఎన్నిక",
    "FLtel": "బ"
  },
  {
    "id": "139152",
    "gen": "female",
    "rel": "Christian",
    "eng": "Briannon",
    "FLeng": "B",
    "tel": "బ్రిఅన్నోన్",
    "FLtel": "బ"
  },
  {
    "id": "139153",
    "gen": "female",
    "rel": "Christian",
    "eng": "Briauna",
    "FLeng": "B",
    "tel": "బ్రియమున",
    "FLtel": "బ"
  },
  {
    "id": "139154",
    "gen": "female",
    "rel": "others",
    "eng": "Bricheve",
    "FLeng": "B",
    "tel": "బరిచేవే",
    "FLtel": "బ"
  },
  {
    "id": "139155",
    "gen": "female",
    "rel": "others",
    "eng": "Brichheve",
    "FLeng": "B",
    "tel": "బ్రిచ్చేవే",
    "FLtel": "బ"
  },
  {
    "id": "139156",
    "gen": "female",
    "rel": "Christian",
    "eng": "Brichterid",
    "FLeng": "B",
    "tel": "బ్రెచ్త్ర్య్డ్",
    "FLtel": "బ"
  },
  {
    "id": "139157",
    "gen": "female",
    "rel": "Christian",
    "eng": "Brichtiua",
    "FLeng": "B",
    "tel": "బరిచితివ",
    "FLtel": "బ"
  },
  {
    "id": "139158",
    "gen": "female",
    "rel": "Christian",
    "eng": "Brichtled",
    "FLeng": "B",
    "tel": "బ్రిచట్లేదు",
    "FLtel": "బ"
  },
  {
    "id": "139159",
    "gen": "female",
    "rel": "Christian",
    "eng": "Brichtrede",
    "FLeng": "B",
    "tel": "బ్రిక్ట్రేడ్",
    "FLtel": "బ"
  },
  {
    "id": "139160",
    "gen": "female",
    "rel": "Christian",
    "eng": "Bricia",
    "FLeng": "B",
    "tel": "బ్రెష",
    "FLtel": "బ"
  },
  {
    "id": "139161",
    "gen": "female",
    "rel": "Christian",
    "eng": "Bricteva",
    "FLeng": "B",
    "tel": "బ్రికేటెవా",
    "FLtel": "బ"
  },
  {
    "id": "139162",
    "gen": "female",
    "rel": "Christian",
    "eng": "Bricthiua",
    "FLeng": "B",
    "tel": "బరిసితివ",
    "FLtel": "బ"
  },
  {
    "id": "139163",
    "gen": "female",
    "rel": "Christian",
    "eng": "Bricthled",
    "FLeng": "B",
    "tel": "బ్రిక్త్ల్డ్",
    "FLtel": "బ"
  },
  {
    "id": "139164",
    "gen": "female",
    "rel": "Christian",
    "eng": "Brictiua",
    "FLeng": "B",
    "tel": "బ్రికేషత్",
    "FLtel": "బ"
  },
  {
    "id": "139165",
    "gen": "female",
    "rel": "Christian",
    "eng": "Brictiva",
    "FLeng": "B",
    "tel": "బ్రిక్టీవ్",
    "FLtel": "బ"
  },
  {
    "id": "139166",
    "gen": "female",
    "rel": "Christian",
    "eng": "Brictled",
    "FLeng": "B",
    "tel": "బ్రిక్ట్ల్డ్",
    "FLtel": "బ"
  },
  {
    "id": "139167",
    "gen": "female",
    "rel": "Christian",
    "eng": "Brictuia",
    "FLeng": "B",
    "tel": "బ్రిక్టుయా",
    "FLtel": "బ"
  },
  {
    "id": "139168",
    "gen": "female",
    "rel": "Christian",
    "eng": "brid",
    "FLeng": "b",
    "tel": "బ్రెడ్",
    "FLtel": "బ"
  },
  {
    "id": "139169",
    "gen": "female",
    "rel": "Christian",
    "eng": "Brid",
    "FLeng": "B",
    "tel": "బ్రెడ్",
    "FLtel": "బ"
  },
  {
    "id": "139170",
    "gen": "female",
    "rel": "Christian",
    "eng": "Brida",
    "FLeng": "B",
    "tel": "బ్రీడ",
    "FLtel": "బ"
  },
  {
    "id": "139171",
    "gen": "female",
    "rel": "Christian",
    "eng": "Bridd",
    "FLeng": "B",
    "tel": "బ్రెడ్",
    "FLtel": "బ"
  },
  {
    "id": "139172",
    "gen": "female",
    "rel": "Christian",
    "eng": "bride",
    "FLeng": "b",
    "tel": "బ్రైడ్",
    "FLtel": "బ"
  },
  {
    "id": "139173",
    "gen": "female",
    "rel": "Christian",
    "eng": "Bridgely",
    "FLeng": "B",
    "tel": "బ్రిడ్జిలై",
    "FLtel": "బ"
  },
  {
    "id": "139174",
    "gen": "female",
    "rel": "Christian",
    "eng": "Bridget",
    "FLeng": "B",
    "tel": "బ్రిడ్జెట్",
    "FLtel": "బ"
  },
  {
    "id": "139175",
    "gen": "female",
    "rel": "Christian",
    "eng": "Bridgett",
    "FLeng": "B",
    "tel": "బ్రిడ్జెట్",
    "FLtel": "బ"
  },
  {
    "id": "139176",
    "gen": "female",
    "rel": "Christian",
    "eng": "Bridgette",
    "FLeng": "B",
    "tel": "బ్రిడ్జెట్టే",
    "FLtel": "బ"
  },
  {
    "id": "139177",
    "gen": "female",
    "rel": "Christian",
    "eng": "Bridgit",
    "FLeng": "B",
    "tel": "బ్రిడ్జిట్",
    "FLtel": "బ"
  },
  {
    "id": "139178",
    "gen": "female",
    "rel": "Christian",
    "eng": "Bridie",
    "FLeng": "B",
    "tel": "బురిడీ",
    "FLtel": "బ"
  },
  {
    "id": "139179",
    "gen": "female",
    "rel": "Christian",
    "eng": "Brie",
    "FLeng": "B",
    "tel": "బ్రియ",
    "FLtel": "బ"
  },
  {
    "id": "139180",
    "gen": "female",
    "rel": "Christian",
    "eng": "Brieana",
    "FLeng": "B",
    "tel": "బ్రియణ",
    "FLtel": "బ"
  },
  {
    "id": "139181",
    "gen": "female",
    "rel": "Christian",
    "eng": "Brieanna",
    "FLeng": "B",
    "tel": "బ్రియేలన్న",
    "FLtel": "బ"
  },
  {
    "id": "139182",
    "gen": "female",
    "rel": "Christian",
    "eng": "Briegh",
    "FLeng": "B",
    "tel": "బ్రిఎగ్",
    "FLtel": "బ"
  },
  {
    "id": "139183",
    "gen": "female",
    "rel": "Christian",
    "eng": "Briela",
    "FLeng": "B",
    "tel": "బ్రియేలా",
    "FLtel": "బ"
  },
  {
    "id": "139184",
    "gen": "female",
    "rel": "Christian",
    "eng": "Briella",
    "FLeng": "B",
    "tel": "బ్రియేల్ల",
    "FLtel": "బ"
  },
  {
    "id": "139185",
    "gen": "female",
    "rel": "Christian",
    "eng": "Brielle",
    "FLeng": "B",
    "tel": "బ్రియేల్ల",
    "FLtel": "బ"
  },
  {
    "id": "139186",
    "gen": "female",
    "rel": "Christian",
    "eng": "Brienda",
    "FLeng": "B",
    "tel": "బ్రిఎండ",
    "FLtel": "బ"
  },
  {
    "id": "139187",
    "gen": "female",
    "rel": "Christian",
    "eng": "Brienna",
    "FLeng": "B",
    "tel": "బ్రియన్న",
    "FLtel": "బ"
  },
  {
    "id": "139188",
    "gen": "female",
    "rel": "Christian",
    "eng": "Brienne",
    "FLeng": "B",
    "tel": "బ్రిఎన్నే",
    "FLtel": "బ"
  },
  {
    "id": "139189",
    "gen": "female",
    "rel": "Christian",
    "eng": "Brier",
    "FLeng": "B",
    "tel": "బ్రిఎర్",
    "FLtel": "బ"
  },
  {
    "id": "139190",
    "gen": "female",
    "rel": "Christian",
    "eng": "Brierley",
    "FLeng": "B",
    "tel": "బ్రిఎర్ల్య్",
    "FLtel": "బ"
  },
  {
    "id": "139191",
    "gen": "female",
    "rel": "Christian",
    "eng": "Brierly",
    "FLeng": "B",
    "tel": "బ్రిఎర్ల్య్",
    "FLtel": "బ"
  },
  {
    "id": "139192",
    "gen": "female",
    "rel": "Christian",
    "eng": "Brietta",
    "FLeng": "B",
    "tel": "బ్రిఎత్తా",
    "FLtel": "బ"
  },
  {
    "id": "139193",
    "gen": "female",
    "rel": "Christian",
    "eng": "Brigetta",
    "FLeng": "B",
    "tel": "బ్రిగెత్త",
    "FLtel": "బ"
  },
  {
    "id": "139194",
    "gen": "female",
    "rel": "Christian",
    "eng": "Brigette",
    "FLeng": "B",
    "tel": "బ్రిగెట్టే",
    "FLtel": "బ"
  },
  {
    "id": "139195",
    "gen": "female",
    "rel": "Christian",
    "eng": "Brighde",
    "FLeng": "B",
    "tel": "బ్రిగ్డ్",
    "FLtel": "బ"
  },
  {
    "id": "139196",
    "gen": "female",
    "rel": "Christian",
    "eng": "Brighid",
    "FLeng": "B",
    "tel": "బ్రిగ్హిద్",
    "FLtel": "బ"
  },
  {
    "id": "139197",
    "gen": "female",
    "rel": "Christian",
    "eng": "brightlyn",
    "FLeng": "b",
    "tel": "బ్రిట్ల్య్న్",
    "FLtel": "బ"
  },
  {
    "id": "139198",
    "gen": "female",
    "rel": "Christian",
    "eng": "Brighton",
    "FLeng": "B",
    "tel": "బ్రిట్న్",
    "FLtel": "బ"
  },
  {
    "id": "139199",
    "gen": "female",
    "rel": "Christian",
    "eng": "Brigid",
    "FLeng": "B",
    "tel": "బ్రిగిడ్",
    "FLtel": "బ"
  },
  {
    "id": "139200",
    "gen": "female",
    "rel": "Christian",
    "eng": "Brigida",
    "FLeng": "B",
    "tel": "బ్రిగుడ",
    "FLtel": "బ"
  },
  {
    "id": "139201",
    "gen": "female",
    "rel": "Christian",
    "eng": "brigidine",
    "FLeng": "b",
    "tel": "బ్రిగెడినే",
    "FLtel": "బ"
  },
  {
    "id": "139202",
    "gen": "female",
    "rel": "Christian",
    "eng": "Brigit",
    "FLeng": "B",
    "tel": "బ్రిజిత్",
    "FLtel": "బ"
  },
  {
    "id": "139203",
    "gen": "female",
    "rel": "Christian",
    "eng": "Brigita",
    "FLeng": "B",
    "tel": "బ్రిజిత",
    "FLtel": "బ"
  },
  {
    "id": "139204",
    "gen": "female",
    "rel": "Christian",
    "eng": "Brigitt",
    "FLeng": "B",
    "tel": "బ్రిజిట్",
    "FLtel": "బ"
  },
  {
    "id": "139205",
    "gen": "female",
    "rel": "Christian",
    "eng": "Brigitta",
    "FLeng": "B",
    "tel": "బ్రిగెత్త",
    "FLtel": "బ"
  },
  {
    "id": "139206",
    "gen": "female",
    "rel": "Christian",
    "eng": "Brigitte",
    "FLeng": "B",
    "tel": "బ్రిగిట్టే",
    "FLtel": "బ"
  },
  {
    "id": "139207",
    "gen": "female",
    "rel": "Hindu",
    "eng": "Brihannala",
    "FLeng": "B",
    "tel": "బ్రిహన్నల",
    "FLtel": "బ"
  },
  {
    "id": "139208",
    "gen": "female",
    "rel": "Hindu",
    "eng": "Brihasmita",
    "FLeng": "B",
    "tel": "బ్రిహస్మితా",
    "FLtel": "బ"
  },
  {
    "id": "139209",
    "gen": "female",
    "rel": "Hindu",
    "eng": "Brihati",
    "FLeng": "B",
    "tel": "బ్రిహతి",
    "FLtel": "బ"
  },
  {
    "id": "139210",
    "gen": "female",
    "rel": "Christian",
    "eng": "Brihctiua",
    "FLeng": "B",
    "tel": "బ్రిహసీషల్",
    "FLtel": "బ"
  },
  {
    "id": "139211",
    "gen": "female",
    "rel": "Christian",
    "eng": "Brihteue",
    "FLeng": "B",
    "tel": "బ్రెహ్ట్యుఎ",
    "FLtel": "బ"
  },
  {
    "id": "139212",
    "gen": "female",
    "rel": "Christian",
    "eng": "Brihtgiua",
    "FLeng": "B",
    "tel": "బ్రెహ్ట్గివ",
    "FLtel": "బ"
  },
  {
    "id": "139213",
    "gen": "female",
    "rel": "Hindu",
    "eng": "Brija",
    "FLeng": "B",
    "tel": "బ్రిజ",
    "FLtel": "బ"
  },
  {
    "id": "139214",
    "gen": "female",
    "rel": "Hindu",
    "eng": "Brijabala",
    "FLeng": "B",
    "tel": "బ్రిజబల",
    "FLtel": "బ"
  },
  {
    "id": "139215",
    "gen": "female",
    "rel": "Hindu",
    "eng": "Brijal",
    "FLeng": "B",
    "tel": "బ్రెజిల్",
    "FLtel": "బ"
  },
  {
    "id": "139216",
    "gen": "female",
    "rel": "Hindu",
    "eng": "Brijbala",
    "FLeng": "B",
    "tel": "బ్రిజిబాల",
    "FLtel": "బ"
  },
  {
    "id": "139217",
    "gen": "female",
    "rel": "Christian",
    "eng": "Brille",
    "FLeng": "B",
    "tel": "బ్రిల్లె",
    "FLtel": "బ"
  },
  {
    "id": "139218",
    "gen": "female",
    "rel": "Christian",
    "eng": "Brilliana",
    "FLeng": "B",
    "tel": "బ్రెల్లిన",
    "FLtel": "బ"
  },
  {
    "id": "139219",
    "gen": "female",
    "rel": "Christian",
    "eng": "Brilynn",
    "FLeng": "B",
    "tel": "బ్రిలీన్",
    "FLtel": "బ"
  },
  {
    "id": "139220",
    "gen": "female",
    "rel": "Christian",
    "eng": "Brin",
    "FLeng": "B",
    "tel": "బ్రిన్",
    "FLtel": "బ"
  },
  {
    "id": "139221",
    "gen": "female",
    "rel": "Christian",
    "eng": "Brina",
    "FLeng": "B",
    "tel": "బ్రిన",
    "FLtel": "బ"
  },
  {
    "id": "139222",
    "gen": "female",
    "rel": "Hindu",
    "eng": "Brinda",
    "FLeng": "B",
    "tel": "బృంద",
    "FLtel": "బ"
  },
  {
    "id": "139223",
    "gen": "female",
    "rel": "Hindu",
    "eng": "Brindavanam",
    "FLeng": "B",
    "tel": "బృందావనం",
    "FLtel": "బ"
  },
  {
    "id": "139224",
    "gen": "female",
    "rel": "Hindu",
    "eng": "Brindavani",
    "FLeng": "B",
    "tel": "బృందావని",
    "FLtel": "బ"
  },
  {
    "id": "139225",
    "gen": "female",
    "rel": "Hindu",
    "eng": "Brindha",
    "FLeng": "B",
    "tel": "బృంద",
    "FLtel": "బ"
  },
  {
    "id": "139226",
    "gen": "female",
    "rel": "Christian",
    "eng": "Brinn",
    "FLeng": "B",
    "tel": "బ్రిన్",
    "FLtel": "బ"
  },
  {
    "id": "139227",
    "gen": "female",
    "rel": "Christian",
    "eng": "Brinxlee",
    "FLeng": "B",
    "tel": "బ్రింక్లీ",
    "FLtel": "బ"
  },
  {
    "id": "139228",
    "gen": "female",
    "rel": "Christian",
    "eng": "Briona",
    "FLeng": "B",
    "tel": "బ్రియన",
    "FLtel": "బ"
  },
  {
    "id": "139229",
    "gen": "female",
    "rel": "Christian",
    "eng": "Brione",
    "FLeng": "B",
    "tel": "బ్రియాన్",
    "FLtel": "బ"
  },
  {
    "id": "139230",
    "gen": "female",
    "rel": "Christian",
    "eng": "Brioni",
    "FLeng": "B",
    "tel": "బిరియాని",
    "FLtel": "బ"
  },
  {
    "id": "139231",
    "gen": "female",
    "rel": "Christian",
    "eng": "Brionna",
    "FLeng": "B",
    "tel": "బ్రియన్న",
    "FLtel": "బ"
  },
  {
    "id": "139232",
    "gen": "female",
    "rel": "Christian",
    "eng": "Brionne",
    "FLeng": "B",
    "tel": "బ్రిన్న్",
    "FLtel": "బ"
  },
  {
    "id": "139233",
    "gen": "female",
    "rel": "Christian",
    "eng": "Briony",
    "FLeng": "B",
    "tel": "బిరియానీ",
    "FLtel": "బ"
  },
  {
    "id": "139234",
    "gen": "female",
    "rel": "Christian",
    "eng": "briony",
    "FLeng": "b",
    "tel": "బిరియానీ",
    "FLtel": "బ"
  },
  {
    "id": "139235",
    "gen": "female",
    "rel": "Christian",
    "eng": "Brisa",
    "FLeng": "B",
    "tel": "బ్రిసా",
    "FLtel": "బ"
  },
  {
    "id": "139236",
    "gen": "female",
    "rel": "Christian",
    "eng": "Briseida",
    "FLeng": "B",
    "tel": "బ్రెసెద",
    "FLtel": "బ"
  },
  {
    "id": "139237",
    "gen": "female",
    "rel": "Christian",
    "eng": "Briseis",
    "FLeng": "B",
    "tel": "బ్రెసెస్",
    "FLtel": "బ"
  },
  {
    "id": "139238",
    "gen": "female",
    "rel": "Christian",
    "eng": "briseis",
    "FLeng": "b",
    "tel": "బ్రెసెస్",
    "FLtel": "బ"
  },
  {
    "id": "139239",
    "gen": "female",
    "rel": "Christian",
    "eng": "Brisen",
    "FLeng": "B",
    "tel": "బ్రెసెన్",
    "FLtel": "బ"
  },
  {
    "id": "139240",
    "gen": "female",
    "rel": "Hindu",
    "eng": "Brisha",
    "FLeng": "B",
    "tel": "బ్రెష",
    "FLtel": "బ"
  },
  {
    "id": "139241",
    "gen": "female",
    "rel": "Hindu",
    "eng": "Brishti",
    "FLeng": "B",
    "tel": "బ్రిష్టి",
    "FLtel": "బ"
  },
  {
    "id": "139242",
    "gen": "female",
    "rel": "Christian",
    "eng": "Brisingamen",
    "FLeng": "B",
    "tel": "బ్రిసింగమేం",
    "FLtel": "బ"
  },
  {
    "id": "139243",
    "gen": "female",
    "rel": "Hindu",
    "eng": "Bristi",
    "FLeng": "B",
    "tel": "బ్రిస్తి",
    "FLtel": "బ"
  }
]