[
  {
    "id": "39529",
    "gen": "male",
    "rel": "Christian",
    "eng": "Skyelar",
    "FLeng": "S",
    "tel": "స్ఖయెలర్",
    "FLtel": "స"
  },
  {
    "id": "39530",
    "gen": "male",
    "rel": "Christian",
    "eng": "Skylah",
    "FLeng": "S",
    "tel": "స్కైలాహ్",
    "FLtel": "స"
  },
  {
    "id": "39531",
    "gen": "male",
    "rel": "Christian",
    "eng": "skyler-2",
    "FLeng": "s",
    "tel": "స్కీలం-౨",
    "FLtel": "స"
  },
  {
    "id": "39532",
    "gen": "male",
    "rel": "Christian",
    "eng": "Skylor",
    "FLeng": "S",
    "tel": "స్కైలా",
    "FLtel": "స"
  },
  {
    "id": "39533",
    "gen": "male",
    "rel": "Christian",
    "eng": "Slade",
    "FLeng": "S",
    "tel": "సలాడ్",
    "FLtel": "స"
  },
  {
    "id": "39534",
    "gen": "male",
    "rel": "Christian",
    "eng": "slade",
    "FLeng": "s",
    "tel": "సలాడ్",
    "FLtel": "స"
  },
  {
    "id": "39535",
    "gen": "male",
    "rel": "Christian",
    "eng": "Sladefield",
    "FLeng": "S",
    "tel": "సలాడేఫిల్డ్",
    "FLtel": "స"
  },
  {
    "id": "39536",
    "gen": "male",
    "rel": "Christian",
    "eng": "Slaed",
    "FLeng": "S",
    "tel": "స్లెడ్",
    "FLtel": "స"
  },
  {
    "id": "39537",
    "gen": "male",
    "rel": "Muslim",
    "eng": "Slaeet",
    "FLeng": "S",
    "tel": "స్లీట్",
    "FLtel": "స"
  },
  {
    "id": "39538",
    "gen": "male",
    "rel": "Christian",
    "eng": "Slaid",
    "FLeng": "S",
    "tel": "స్లైడ్",
    "FLtel": "స"
  },
  {
    "id": "39539",
    "gen": "male",
    "rel": "Christian",
    "eng": "Slaide",
    "FLeng": "S",
    "tel": "స్లైడ్",
    "FLtel": "స"
  },
  {
    "id": "39540",
    "gen": "male",
    "rel": "Christian",
    "eng": "slash",
    "FLeng": "s",
    "tel": "స్లాష్",
    "FLtel": "స"
  },
  {
    "id": "39541",
    "gen": "male",
    "rel": "Christian",
    "eng": "Slate",
    "FLeng": "S",
    "tel": "స్లాట్",
    "FLtel": "స"
  },
  {
    "id": "39542",
    "gen": "male",
    "rel": "Christian",
    "eng": "Slater",
    "FLeng": "S",
    "tel": "స్లేటర్",
    "FLtel": "స"
  },
  {
    "id": "39543",
    "gen": "male",
    "rel": "Christian",
    "eng": "Slaton",
    "FLeng": "S",
    "tel": "స్లతోన్",
    "FLtel": "స"
  },
  {
    "id": "39544",
    "gen": "male",
    "rel": "Christian",
    "eng": "Slava",
    "FLeng": "S",
    "tel": "సలవా",
    "FLtel": "స"
  },
  {
    "id": "39545",
    "gen": "male",
    "rel": "Christian",
    "eng": "Slavco",
    "FLeng": "S",
    "tel": "స్లావ్కో",
    "FLtel": "స"
  },
  {
    "id": "39546",
    "gen": "male",
    "rel": "Christian",
    "eng": "Slaven",
    "FLeng": "S",
    "tel": "స్లావేం",
    "FLtel": "స"
  },
  {
    "id": "39547",
    "gen": "male",
    "rel": "Christian",
    "eng": "Slavik",
    "FLeng": "S",
    "tel": "స్లావిక్",
    "FLtel": "స"
  },
  {
    "id": "39548",
    "gen": "male",
    "rel": "Christian",
    "eng": "Slavoma­r",
    "FLeng": "S",
    "tel": "స్లావోమా­ర్",
    "FLtel": "స"
  },
  {
    "id": "39549",
    "gen": "male",
    "rel": "Christian",
    "eng": "Slawek",
    "FLeng": "S",
    "tel": "స్లావెక్",
    "FLtel": "స"
  },
  {
    "id": "39550",
    "gen": "male",
    "rel": "Christian",
    "eng": "Slawomir",
    "FLeng": "S",
    "tel": "స్లావమిర్",
    "FLtel": "స"
  },
  {
    "id": "39551",
    "gen": "male",
    "rel": "Christian",
    "eng": "Slayde",
    "FLeng": "S",
    "tel": "స్లయిడ్",
    "FLtel": "స"
  },
  {
    "id": "39552",
    "gen": "male",
    "rel": "Christian",
    "eng": "Slayden",
    "FLeng": "S",
    "tel": "సలేదేం",
    "FLtel": "స"
  },
  {
    "id": "39553",
    "gen": "male",
    "rel": "Christian",
    "eng": "Slayton",
    "FLeng": "S",
    "tel": "స్లయితుం",
    "FLtel": "స"
  },
  {
    "id": "39554",
    "gen": "male",
    "rel": "Christian",
    "eng": "Slean",
    "FLeng": "S",
    "tel": "స్లీమన్",
    "FLtel": "స"
  },
  {
    "id": "39555",
    "gen": "male",
    "rel": "Christian",
    "eng": "Sledda",
    "FLeng": "S",
    "tel": "స్లేడ్డ",
    "FLtel": "స"
  },
  {
    "id": "39556",
    "gen": "male",
    "rel": "Christian",
    "eng": "Sliden",
    "FLeng": "S",
    "tel": "స్లిదేం",
    "FLtel": "స"
  },
  {
    "id": "39557",
    "gen": "male",
    "rel": "Christian",
    "eng": "Sloan",
    "FLeng": "S",
    "tel": "స్లోత్న్",
    "FLtel": "స"
  },
  {
    "id": "39558",
    "gen": "male",
    "rel": "Christian",
    "eng": "Sloane",
    "FLeng": "S",
    "tel": "స్లోన్",
    "FLtel": "స"
  },
  {
    "id": "39559",
    "gen": "male",
    "rel": "Christian",
    "eng": "Slobodan",
    "FLeng": "S",
    "tel": "స్లొబోదన్",
    "FLtel": "స"
  },
  {
    "id": "39560",
    "gen": "male",
    "rel": "Hindu",
    "eng": "Slokh",
    "FLeng": "S",
    "tel": "శ్లోకః",
    "FLtel": "శ"
  },
  {
    "id": "39561",
    "gen": "male",
    "rel": "Christian",
    "eng": "Slone",
    "FLeng": "S",
    "tel": "సలోన్",
    "FLtel": "స"
  },
  {
    "id": "39562",
    "gen": "male",
    "rel": "Christian",
    "eng": "Sly",
    "FLeng": "S",
    "tel": "స్ల్య్",
    "FLtel": "స"
  },
  {
    "id": "39563",
    "gen": "male",
    "rel": "Muslim",
    "eng": "Smad",
    "FLeng": "S",
    "tel": "స్మాద్",
    "FLtel": "స"
  },
  {
    "id": "39564",
    "gen": "male",
    "rel": "Hindu",
    "eng": "Smarabhu",
    "FLeng": "S",
    "tel": "స్మరభు",
    "FLtel": "స"
  },
  {
    "id": "39565",
    "gen": "male",
    "rel": "Hindu",
    "eng": "Smarajit",
    "FLeng": "S",
    "tel": "స్మరజిత్",
    "FLtel": "స"
  },
  {
    "id": "39566",
    "gen": "male",
    "rel": "Hindu",
    "eng": "Smaram",
    "FLeng": "S",
    "tel": "సమరం",
    "FLtel": "స"
  },
  {
    "id": "39567",
    "gen": "male",
    "rel": "Hindu",
    "eng": "Smaran",
    "FLeng": "S",
    "tel": "సమరం",
    "FLtel": "స"
  },
  {
    "id": "39568",
    "gen": "male",
    "rel": "Hindu",
    "eng": "Smayan",
    "FLeng": "S",
    "tel": "సమయం",
    "FLtel": "స"
  },
  {
    "id": "39569",
    "gen": "male",
    "rel": "Christian",
    "eng": "Smedleigh",
    "FLeng": "S",
    "tel": "స్మేడ్లేఇఘ్",
    "FLtel": "స"
  },
  {
    "id": "39570",
    "gen": "male",
    "rel": "Christian",
    "eng": "Smedley",
    "FLeng": "S",
    "tel": "స్మెడ్ల్య్",
    "FLtel": "స"
  },
  {
    "id": "39571",
    "gen": "male",
    "rel": "Christian",
    "eng": "Smedly",
    "FLeng": "S",
    "tel": "స్మెడ్లీ",
    "FLtel": "స"
  },
  {
    "id": "39572",
    "gen": "male",
    "rel": "Muslim",
    "eng": "Smeer",
    "FLeng": "S",
    "tel": "సమీర్",
    "FLtel": "స"
  },
  {
    "id": "39573",
    "gen": "male",
    "rel": "Hindu",
    "eng": "Smeet",
    "FLeng": "S",
    "tel": "సమీత్",
    "FLtel": "స"
  },
  {
    "id": "39574",
    "gen": "male",
    "rel": "Christian",
    "eng": "Smetheleah",
    "FLeng": "S",
    "tel": "స్మేతెలీహ్",
    "FLtel": "స"
  },
  {
    "id": "39575",
    "gen": "male",
    "rel": "Christian",
    "eng": "Smia°r",
    "FLeng": "S",
    "tel": "స్మిత్°ర్",
    "FLtel": "స"
  },
  {
    "id": "39576",
    "gen": "male",
    "rel": "Hindu",
    "eng": "Smiren",
    "FLeng": "S",
    "tel": "స్మిరేం",
    "FLtel": "స"
  },
  {
    "id": "39577",
    "gen": "male",
    "rel": "Hindu",
    "eng": "Smirit",
    "FLeng": "S",
    "tel": "సుమిరైట్",
    "FLtel": "స"
  },
  {
    "id": "39578",
    "gen": "male",
    "rel": "Hindu",
    "eng": "Smiritivan",
    "FLeng": "S",
    "tel": "స్మిరితీవన్",
    "FLtel": "స"
  },
  {
    "id": "39579",
    "gen": "male",
    "rel": "Hindu",
    "eng": "Smit",
    "FLeng": "S",
    "tel": "స్మిత్",
    "FLtel": "స"
  },
  {
    "id": "39580",
    "gen": "male",
    "rel": "Hindu",
    "eng": "Smitavaktra",
    "FLeng": "S",
    "tel": "స్మితవక్త్ర",
    "FLtel": "స"
  },
  {
    "id": "39581",
    "gen": "male",
    "rel": "Hindu",
    "eng": "Smitesh",
    "FLeng": "S",
    "tel": "సమితేష్",
    "FLtel": "స"
  },
  {
    "id": "39582",
    "gen": "male",
    "rel": "Hindu",
    "eng": "Smith",
    "FLeng": "S",
    "tel": "స్మిత్",
    "FLtel": "స"
  },
  {
    "id": "39583",
    "gen": "male",
    "rel": "Christian",
    "eng": "smith",
    "FLeng": "s",
    "tel": "స్మిత్",
    "FLtel": "స"
  },
  {
    "id": "39584",
    "gen": "male",
    "rel": "Hindu",
    "eng": "Smitraj",
    "FLeng": "S",
    "tel": "సుమిత్రాజ్",
    "FLtel": "స"
  },
  {
    "id": "39585",
    "gen": "male",
    "rel": "Christian",
    "eng": "Smitty",
    "FLeng": "S",
    "tel": "స్మిట్టి",
    "FLtel": "స"
  },
  {
    "id": "39586",
    "gen": "male",
    "rel": "Christian",
    "eng": "smoke",
    "FLeng": "s",
    "tel": "స్మోక్",
    "FLtel": "స"
  },
  {
    "id": "39587",
    "gen": "male",
    "rel": "Hindu",
    "eng": "Smritiman",
    "FLeng": "S",
    "tel": "స్మ్రితిమం",
    "FLtel": "స"
  },
  {
    "id": "39588",
    "gen": "male",
    "rel": "Hindu",
    "eng": "Smyan",
    "FLeng": "S",
    "tel": "సమయం",
    "FLtel": "స"
  },
  {
    "id": "39589",
    "gen": "male",
    "rel": "Christian",
    "eng": "Smyth",
    "FLeng": "S",
    "tel": "సుమిత్",
    "FLtel": "స"
  },
  {
    "id": "39590",
    "gen": "male",
    "rel": "Christian",
    "eng": "Smythe",
    "FLeng": "S",
    "tel": "సమైతే",
    "FLtel": "స"
  },
  {
    "id": "39591",
    "gen": "male",
    "rel": "Hindu",
    "eng": "Snaaru",
    "FLeng": "S",
    "tel": "స్నారు",
    "FLtel": "స"
  },
  {
    "id": "39592",
    "gen": "male",
    "rel": "Christian",
    "eng": "Snaroc",
    "FLeng": "S",
    "tel": "స్నారోచ్",
    "FLtel": "స"
  },
  {
    "id": "39593",
    "gen": "male",
    "rel": "Sikh",
    "eng": "Snatam",
    "FLeng": "S",
    "tel": "స్నాతం",
    "FLtel": "స"
  },
  {
    "id": "39594",
    "gen": "male",
    "rel": "Sikh",
    "eng": "Snawar",
    "FLeng": "S",
    "tel": "స్నావర్",
    "FLtel": "స"
  },
  {
    "id": "39595",
    "gen": "male",
    "rel": "Hindu",
    "eng": "Sneagen",
    "FLeng": "S",
    "tel": "స్నేఆగేం",
    "FLtel": "స"
  },
  {
    "id": "39596",
    "gen": "male",
    "rel": "Hindu",
    "eng": "Snehakant",
    "FLeng": "S",
    "tel": "స్నేహకాంత్",
    "FLtel": "స"
  },
  {
    "id": "39597",
    "gen": "male",
    "rel": "Hindu",
    "eng": "Snehaman",
    "FLeng": "S",
    "tel": "స్నేహమన్",
    "FLtel": "స"
  },
  {
    "id": "39598",
    "gen": "male",
    "rel": "Hindu",
    "eng": "Snehan",
    "FLeng": "S",
    "tel": "స్నేహం",
    "FLtel": "స"
  },
  {
    "id": "39599",
    "gen": "male",
    "rel": "Hindu",
    "eng": "Snehanshn",
    "FLeng": "S",
    "tel": "స్నేహాంష్ణ",
    "FLtel": "స"
  },
  {
    "id": "39600",
    "gen": "male",
    "rel": "Hindu",
    "eng": "Snehardh",
    "FLeng": "S",
    "tel": "స్నేహార్ద్",
    "FLtel": "స"
  },
  {
    "id": "39601",
    "gen": "male",
    "rel": "Hindu",
    "eng": "Sneharsh",
    "FLeng": "S",
    "tel": "స్నేహార్ష్",
    "FLtel": "స"
  },
  {
    "id": "39602",
    "gen": "male",
    "rel": "Hindu",
    "eng": "Snehashis",
    "FLeng": "S",
    "tel": "స్నేహశీష్",
    "FLtel": "స"
  },
  {
    "id": "39603",
    "gen": "male",
    "rel": "Hindu",
    "eng": "Snehasish",
    "FLeng": "S",
    "tel": "స్నేహశీష్",
    "FLtel": "స"
  },
  {
    "id": "39604",
    "gen": "male",
    "rel": "Hindu",
    "eng": "Snehil",
    "FLeng": "S",
    "tel": "స్నేహిల్",
    "FLtel": "స"
  },
  {
    "id": "39605",
    "gen": "male",
    "rel": "Hindu",
    "eng": "Snehin",
    "FLeng": "S",
    "tel": "స్నేహిం",
    "FLtel": "స"
  },
  {
    "id": "39606",
    "gen": "male",
    "rel": "Hindu",
    "eng": "Snehit",
    "FLeng": "S",
    "tel": "స్నేహిత్",
    "FLtel": "స"
  },
  {
    "id": "39607",
    "gen": "male",
    "rel": "Hindu",
    "eng": "Snehith",
    "FLeng": "S",
    "tel": "స్నేహిత్",
    "FLtel": "స"
  },
  {
    "id": "39608",
    "gen": "male",
    "rel": "Hindu",
    "eng": "Snehu",
    "FLeng": "S",
    "tel": "స్నేహి",
    "FLtel": "స"
  },
  {
    "id": "39609",
    "gen": "male",
    "rel": "Hindu",
    "eng": "Snesh",
    "FLeng": "S",
    "tel": "స్నెస్",
    "FLtel": "స"
  },
  {
    "id": "39610",
    "gen": "male",
    "rel": "Hindu",
    "eng": "Snithik",
    "FLeng": "S",
    "tel": "సన్నిథిక్",
    "FLtel": "స"
  },
  {
    "id": "39611",
    "gen": "male",
    "rel": "Christian",
    "eng": "snorri",
    "FLeng": "s",
    "tel": "స్నోర్రి",
    "FLtel": "స"
  },
  {
    "id": "39612",
    "gen": "male",
    "rel": "Christian",
    "eng": "Snowden",
    "FLeng": "S",
    "tel": "సనౌదేం",
    "FLtel": "స"
  },
  {
    "id": "39613",
    "gen": "male",
    "rel": "Christian",
    "eng": "Snowdon",
    "FLeng": "S",
    "tel": "సనౌడొం",
    "FLtel": "స"
  },
  {
    "id": "39614",
    "gen": "male",
    "rel": "Christian",
    "eng": "Snytra",
    "FLeng": "S",
    "tel": "శనిత్ర",
    "FLtel": "శ"
  },
  {
    "id": "39615",
    "gen": "male",
    "rel": "Christian",
    "eng": "So",
    "FLeng": "S",
    "tel": "సో",
    "FLtel": "స"
  },
  {
    "id": "39616",
    "gen": "male",
    "rel": "Muslim",
    "eng": "Soad",
    "FLeng": "S",
    "tel": "సోల్డ్",
    "FLtel": "స"
  },
  {
    "id": "39617",
    "gen": "male",
    "rel": "Hindu",
    "eng": "Soanjan",
    "FLeng": "S",
    "tel": "సోఆంజన్",
    "FLtel": "స"
  },
  {
    "id": "39618",
    "gen": "male",
    "rel": "Muslim",
    "eng": "Sobah",
    "FLeng": "S",
    "tel": "శోభ",
    "FLtel": "శ"
  },
  {
    "id": "39619",
    "gen": "male",
    "rel": "Muslim",
    "eng": "Soban",
    "FLeng": "S",
    "tel": "శోభన్",
    "FLtel": "శ"
  },
  {
    "id": "39620",
    "gen": "male",
    "rel": "Christian",
    "eng": "Soba¬slav",
    "FLeng": "S",
    "tel": "శోభ¬స్లాప్",
    "FLtel": "శ"
  }
]